sqlite_utils_shell.py
sqlite_utils_shell-0.3.dist-info/LICENSE
sqlite_utils_shell-0.3.dist-info/METADATA
sqlite_utils_shell-0.3.dist-info/WHEEL
sqlite_utils_shell-0.3.dist-info/entry_points.txt
sqlite_utils_shell-0.3.dist-info/top_level.txt
sqlite_utils_shell-0.3.dist-info/RECORD
