Metadata-Version: 2.1
Name: sqlite-utils-shell
Version: 0.3
Summary: An interactive shell for sqlite-utils
Author: Simon Willison
License: Apache-2.0
Project-URL: Homepage, https://github.com/simonw/sqlite-utils-shell
Project-URL: Changelog, https://github.com/simonw/sqlite-utils-shell/releases
Project-URL: Issues, https://github.com/simonw/sqlite-utils-shell/issues
Project-URL: CI, https://github.com/simonw/sqlite-utils-shell/actions
Classifier: License :: OSI Approved :: Apache Software License
License-File: LICENSE
Requires-Dist: sqlite-utils
Provides-Extra: test
Requires-Dist: pytest ; extra == 'test'
